vectormpp/__init__.py
vectormpp/__main__.py
vectormpp/client.py
vectormpp/executor.py
vectormpp/loggers.py
vectormpp/manifest.py
vectormpp-0.2.6.dist-info/METADATA
vectormpp-0.2.6.dist-info/WHEEL
vectormpp-0.2.6.dist-info/entry_points.txt
vectormpp-0.2.6.dist-info/top_level.txt
vectormpp-0.2.6.dist-info/RECORD
