Metadata-Version: 2.1
Name: vectormpp
Version: 0.2.6
Summary: Actian VectorMPP Installer
Author-email: Rui Xiao <rui.xiao@hcl-software.com>
Project-URL: Homepage, https://www.actian.com/databases/vector/
Requires-Python: >=3.6
Requires-Dist: PyYAML
